image_text_structurizer/__init__.py
image_text_structurizer/main.py
image_text_structurizer/prompts.py
image_text_structurizer-2025.12.21124037.dist-info/METADATA
image_text_structurizer-2025.12.21124037.dist-info/WHEEL
image_text_structurizer-2025.12.21124037.dist-info/top_level.txt
image_text_structurizer-2025.12.21124037.dist-info/RECORD
