Metadata-Version: 2.4
Name: image-text-structurizer
Version: 2025.12.21124037
Summary: A new package that processes user-provided text descriptions of images and returns structured, validated outputs using pattern matching. It ensures that the generated content adheres to a predefined f
Author-email: image-text-structurizer <hi@eugene.plus>
License: MIT
Project-URL: Homepage, https://github.com/chigwell/image-text-structurizer
Requires-Python: >=3.9
Requires-Dist: langchain-llm7>=0.0.0
Requires-Dist: llmatch-messages>=0.0.0
Requires-Dist: langchain-core>=0.3.0
